LICENSE.rst
haapi/games/common/__init__.py
haapi/games/common/gcp/__init__.py
haapi/games/common/py.typed
haapi.games.common-0.2.0.dist-info/LICENSE.rst
haapi.games.common-0.2.0.dist-info/WHEEL
haapi.games.common-0.2.0.dist-info/METADATA
haapi.games.common-0.2.0.dist-info/RECORD
