Metadata-Version: 2.1
Name: haapi.games.common
Version: 0.2.0
Summary: Haapi Games Common
Home-page: https://github.com/Haapi-Games/haapi.games.common
License: MIT
Author: Haapi
Author-email: haapigeek@gmail.com
Requires-Python: >=3.6.1,<4.0.0
Classifier: License :: OSI Approved :: MIT License
Classifier: Programming Language :: Python :: 3
Classifier: Programming Language :: Python :: 3.6
Classifier: Programming Language :: Python :: 3.7
Classifier: Programming Language :: Python :: 3.8
Classifier: Programming Language :: Python :: 3.9
Requires-Dist: google-cloud-secret-manager (>=2.2.0,<3.0.0)
Project-URL: Changelog, https://github.com/Haapi-Games/haapi.games.common/releases
Project-URL: Documentation, https://haapigamescommon.readthedocs.io
Project-URL: Repository, https://github.com/Haapi-Games/haapi.games.common
